FIREcaller/FIREcaller.py
FIREcaller/__init__.py
FIREcaller-1.0.0.dist-info/LICENSE
FIREcaller-1.0.0.dist-info/METADATA
FIREcaller-1.0.0.dist-info/WHEEL
FIREcaller-1.0.0.dist-info/entry_points.txt
FIREcaller-1.0.0.dist-info/top_level.txt
FIREcaller-1.0.0.dist-info/RECORD
