Metadata-Version: 2.1
Name: FIREcaller
Version: 1.0.0
Summary: Python library for detecting Frequently Interacting REgions (FIREs) from Hi-C data
Home-page: https://github.com/cellular-genomics/python-FIREcaller
Author: Jakub Lipiński
Author-email: jakub@cellular-genomics.com
License: UNKNOWN
Platform: UNKNOWN
Classifier: Programming Language :: Python :: 3
Classifier: License :: OSI Approved :: Apache Software License
Classifier: Operating System :: OS Independent
Classifier: Topic :: Scientific/Engineering :: Bio-Informatics
Requires-Python: >=3.6
Requires-Dist: cooler (>=0.8.7)
Requires-Dist: pandas (>=1.0.1)
Requires-Dist: statsmodels (>=0.11.0)
Requires-Dist: dask (>=2.10.1)
Requires-Dist: fsspec (>=0.6.2)
Requires-Dist: tables (>=3.6.1)
